ab_core/database/__init__.py
ab_core/database/session_context.py
ab_core/database/databases/__init__.py
ab_core/database/databases/base.py
ab_core/database/databases/sqlalchemy.py
ab_core/database/databases/template.py
ab_core/database/mixins/__init__.py
ab_core/database/mixins/active.py
ab_core/database/mixins/archived.py
ab_core/database/mixins/created_at.py
ab_core/database/mixins/created_by.py
ab_core/database/mixins/deleted.py
ab_core/database/mixins/id.py
ab_core/database/mixins/name.py
ab_core/database/mixins/slug.py
ab_core/database/mixins/updated_at.py
ab_core/database/mixins/updated_by.py
ab_core/database/schema/__init__.py
ab_core/database/schema/database_type.py
ab_database-0.2.4.dist-info/METADATA
ab_database-0.2.4.dist-info/WHEEL
ab_database-0.2.4.dist-info/licenses/LICENSE
ab_database-0.2.4.dist-info/RECORD
