Metadata-Version: 2.4
Name: ab-database
Version: 0.2.4
Author-email: Matthew Coulter <53892067+mattcoulter7@users.noreply.github.com>
License-File: LICENSE
Requires-Python: <4,>=3.12
Requires-Dist: ab-dependency<0.3.0,>=0.2.0
Requires-Dist: pydantic<3,>=2.11.7
Requires-Dist: slugify<0.0.2,>=0.0.1
Requires-Dist: sqlmodel<0.0.25,>=0.0.24
Requires-Dist: uuid7<0.2,>=0.1.0
Provides-Extra: all
Requires-Dist: aiomysql<0.3,>=0.2.0; extra == 'all'
Requires-Dist: aioodbc<0.6,>=0.5.0; extra == 'all'
Requires-Dist: aiosqlite<0.22,>=0.21.0; extra == 'all'
Requires-Dist: asyncpg<0.31,>=0.30.0; extra == 'all'
Requires-Dist: clickhouse-connect<1,>=0.7; extra == 'all'
Requires-Dist: cockroachdb<0.4,>=0.3.5; extra == 'all'
Requires-Dist: firebird-driver<3,>=2.0.2; extra == 'all'
Requires-Dist: ibm-db-sa<0.5,>=0.4.1; extra == 'all'
Requires-Dist: ibm-db<4,>=3.2.6; extra == 'all'
Requires-Dist: mariadb<2,>=1.1.12; extra == 'all'
Requires-Dist: mysqlclient<3,>=2.2.7; extra == 'all'
Requires-Dist: oracledb<4,>=3.1.1; extra == 'all'
Requires-Dist: psycopg[binary]<4,>=3.1; extra == 'all'
Requires-Dist: pyodbc<6,>=5.2.0; extra == 'all'
Requires-Dist: snowflake-sqlalchemy<2,>=1.7.4; extra == 'all'
Requires-Dist: sqlalchemy-firebird<3,>=2.1.0; extra == 'all'
Requires-Dist: sqlalchemy-sybase<3,>=2.0.0; extra == 'all'
Requires-Dist: sqlalchemy-trino<0.6,>=0.5.0; extra == 'all'
Requires-Dist: sqlalchemy-vertica-python<0.7,>=0.6.3; extra == 'all'
Requires-Dist: vertica-python<2,>=1.4.0; extra == 'all'
Provides-Extra: clickhouse-sync
Requires-Dist: clickhouse-connect<1,>=0.7; extra == 'clickhouse-sync'
Provides-Extra: cockroach-sync
Requires-Dist: cockroachdb<0.4,>=0.3.5; extra == 'cockroach-sync'
Provides-Extra: firebird-sync
Requires-Dist: firebird-driver<3,>=2.0.2; extra == 'firebird-sync'
Requires-Dist: sqlalchemy-firebird<3,>=2.1.0; extra == 'firebird-sync'
Provides-Extra: ibm-db2-sync
Requires-Dist: ibm-db-sa<0.5,>=0.4.1; extra == 'ibm-db2-sync'
Requires-Dist: ibm-db<4,>=3.2.6; extra == 'ibm-db2-sync'
Provides-Extra: mariadb-sync
Requires-Dist: mariadb<2,>=1.1.12; extra == 'mariadb-sync'
Provides-Extra: mssql-async
Requires-Dist: aioodbc<0.6,>=0.5.0; extra == 'mssql-async'
Provides-Extra: mssql-sync
Requires-Dist: pyodbc<6,>=5.2.0; extra == 'mssql-sync'
Provides-Extra: mysql-async
Requires-Dist: aiomysql<0.3,>=0.2.0; extra == 'mysql-async'
Provides-Extra: mysql-sync
Requires-Dist: mysqlclient<3,>=2.2.7; extra == 'mysql-sync'
Provides-Extra: oracle-sync
Requires-Dist: oracledb<4,>=3.1.1; extra == 'oracle-sync'
Provides-Extra: postgres-async
Requires-Dist: asyncpg<0.31,>=0.30.0; extra == 'postgres-async'
Provides-Extra: postgres-sync
Requires-Dist: psycopg[binary]<4,>=3.1; extra == 'postgres-sync'
Provides-Extra: snowflake-sync
Requires-Dist: snowflake-sqlalchemy<2,>=1.7.4; extra == 'snowflake-sync'
Provides-Extra: sqlite-async
Requires-Dist: aiosqlite<0.22,>=0.21.0; extra == 'sqlite-async'
Provides-Extra: sybase-sync
Requires-Dist: sqlalchemy-sybase<3,>=2.0.0; extra == 'sybase-sync'
Provides-Extra: trino-sync
Requires-Dist: sqlalchemy-trino<0.6,>=0.5.0; extra == 'trino-sync'
Provides-Extra: vertica-sync
Requires-Dist: sqlalchemy-vertica-python<0.7,>=0.6.3; extra == 'vertica-sync'
Requires-Dist: vertica-python<2,>=1.4.0; extra == 'vertica-sync'
